torchvision4ad/__init__.py
torchvision4ad/datasets/__init__.py
torchvision4ad/datasets/mvtec.py
torchvision4ad-0.1.2.dist-info/LICENSE
torchvision4ad-0.1.2.dist-info/METADATA
torchvision4ad-0.1.2.dist-info/WHEEL
torchvision4ad-0.1.2.dist-info/top_level.txt
torchvision4ad-0.1.2.dist-info/RECORD
