Metadata-Version: 2.1
Name: torchvision4ad
Version: 0.1.2
Summary: torchvision for anomaly detection
Home-page: https://github.com/A03ki/torchvision4ad
Author: A03ki
Author-email: a03ki04@gmail.com
License: MIT
Keywords: torchvision anomaly detection
Platform: UNKNOWN
Classifier: License :: OSI Approved :: MIT License
Requires-Dist: torchvision
